tepkit/__init__.py
tepkit/cli/__init__.py
tepkit/cli/_logger.py
tepkit/cli/typer/__init__.py
tepkit/cli/typer/app.py
tepkit/cli/typer/commands_data.py
tepkit/cli/typer/docstring_to_typer.py
tepkit/cli/typer/entry.py
tepkit/cli/typer/utils.py
tepkit/config.py
tepkit/core/__init__.py
tepkit/core/atom.py
tepkit/core/geometry.py
tepkit/core/high_symmetry_points.py
tepkit/core/structure.py
tepkit/core/symmetry.py
tepkit/core/symmetry_data.py
tepkit/core/vasp.py
tepkit/formulas/__init__.py
tepkit/formulas/dp.py
tepkit/formulas/thermoelectric.py
tepkit/functions/__init__.py
tepkit/functions/custom/__init__.py
tepkit/functions/custom/example.py
tepkit/functions/direct/__init__.py
tepkit/functions/direct/dp.py
tepkit/functions/phonopy/__init__.py
tepkit/functions/phonopy/rms.py
tepkit/functions/shengbte/__init__.py
tepkit/functions/shengbte/poscar_to_control.py
tepkit/functions/symmetry/__init__.py
tepkit/functions/thirdorder/__init__.py
tepkit/functions/thirdorder/action.py
tepkit/functions/thirdorder/check.py
tepkit/functions/thirdorder/repost.py
tepkit/functions/thirdorder/rms.py
tepkit/functions/vasp/__init__.py
tepkit/functions/vasp/_system.py
tepkit/functions/vasp/band_contour.py
tepkit/functions/vasp/check_state.py
tepkit/functions/vasp/get_band.py
tepkit/functions/vasp/get_high_symmetry_points.py
tepkit/functions/vasp/get_neighbor_distances.py
tepkit/functions/vasp/get_piezoelectric_stress_tensors.py
tepkit/functions/vasp/get_thickness_info.py
tepkit/functions/vasp/kpoints_tools.py
tepkit/functions/vasp/poscar_tools.py
tepkit/io/__init__.py
tepkit/io/boltztrap2.py
tepkit/io/indices.py
tepkit/io/mlip/__init__.py
tepkit/io/output.py
tepkit/io/phonopy/__init__.py
tepkit/io/phonopy/_force_constants.py
tepkit/io/shengbte/__init__.py
tepkit/io/shengbte/_control.py
tepkit/io/shengbte/_file_types.py
tepkit/io/shengbte/_force_constants_3rd.py
tepkit/io/shengbte/_kappa_files.py
tepkit/io/shengbte/_omega_files.py
tepkit/io/vasp/__init__.py
tepkit/io/vasp/_eigenval.py
tepkit-0.2.1.dist-info/entry_points.txt
tepkit-0.2.1.dist-info/licenses/LICENSE
tepkit-0.2.1.dist-info/METADATA
tepkit-0.2.1.dist-info/WHEEL
tepkit-0.2.1.dist-info/RECORD
