Metadata-Version: 2.4
Name: tepkit
Version: 0.2.1
Summary: A user-friendly program for accelerating the calculation and analysis processes of transport, electronic, and thermoelectric properties of materials.
License-File: LICENSE
Author: Shu-Hao Cao
Author-email: csh.academic@gmail.com
Requires-Python: >=3.11
Classifier: Programming Language :: Python :: 3
Classifier: Programming Language :: Python :: 3.11
Classifier: Programming Language :: Python :: 3.12
Classifier: Programming Language :: Python :: 3.13
Classifier: Programming Language :: Python :: 3.14
Provides-Extra: all
Provides-Extra: doc
Requires-Dist: docstring_parser
Requires-Dist: f90nml ; extra == "all"
Requires-Dist: loguru
Requires-Dist: matplotlib
Requires-Dist: mendeleev ; extra == "all"
Requires-Dist: myst-parser ; extra == "doc"
Requires-Dist: numpy
Requires-Dist: pandas
Requires-Dist: pymatgen ; extra == "all"
Requires-Dist: rich ; extra == "all"
Requires-Dist: scipy
Requires-Dist: spglib ; extra == "all"
Requires-Dist: sphinx ; extra == "doc"
Requires-Dist: sphinx-autoapi ; extra == "doc"
Requires-Dist: sphinx-book-theme ; extra == "doc"
Requires-Dist: sphinxcontrib-mermaid ; extra == "doc"
Requires-Dist: toml
Requires-Dist: tqdm
Requires-Dist: typer
